mdx_math_img.py
mdx_math_img-0.10.dist-info/LICENSE
mdx_math_img-0.10.dist-info/METADATA
mdx_math_img-0.10.dist-info/WHEEL
mdx_math_img-0.10.dist-info/entry_points.txt
mdx_math_img-0.10.dist-info/top_level.txt
mdx_math_img-0.10.dist-info/RECORD
